bnet/__init__.py
bnet/client.py
bnet/connection.py
bnet/exceptions.py
bnet/version.py
bnet-0.2.dist-info/DESCRIPTION.rst
bnet-0.2.dist-info/METADATA
bnet-0.2.dist-info/RECORD
bnet-0.2.dist-info/WHEEL
bnet-0.2.dist-info/metadata.json
bnet-0.2.dist-info/top_level.txt
